{"$id":"1","$type":"Blockhub.Profile, Blockhub.Core","ImageUri":null,"Notifications":null,"ProfileObjects":{"$type":"System.Collections.ObjectModel.Collection`1[[Blockhub.ProfileObject, Blockhub.Core]], mscorlib","$values":[{"$id":"2","$type":"Blockhub.Wallet.Wallet`1[[Blockhub.Ethereum.Ethereum, Blockhub.Ethereum]], Blockhub.Core","Accounts":{"$type":"System.Collections.ObjectModel.Collection`1[[Blockhub.Wallet.Account`1[[Blockhub.Ethereum.Ethereum, Blockhub.Ethereum]], Blockhub.Core]], mscorlib","$values":[{"$id":"3","$type":"Blockhub.Wallet.Account`1[[Blockhub.Ethereum.Ethereum, Blockhub.Ethereum]], Blockhub.Core","Wallet":{"$ref":"2"},"Address":"0x627306090abaB3A6e1400e9345bC60c78a8BEf57","Id":"f979390b-9982-4c4a-8334-3519223248bf","Name":""},{"$id":"4","$type":"Blockhub.Wallet.Account`1[[Blockhub.Ethereum.Ethereum, Blockhub.Ethereum]], Blockhub.Core","Wallet":{"$ref":"2"},"Address":"0xf17f52151EbEF6C7334FAD080c5704D77216b732","Id":"beada85b-5efd-4ea7-84b1-65740f191284","Name":""},{"$id":"5","$type":"Blockhub.Wallet.Account`1[[Blockhub.Ethereum.Ethereum, Blockhub.Ethereum]], Blockhub.Core","Wallet":{"$ref":"2"},"Address":"0xC5fdf4076b8F3A5357c5E395ab970B5B54098Fef","Id":"44115265-7b70-46ed-9b81-00fb7a5a426d","Name":""},{"$id":"6","$type":"Blockhub.Wallet.Account`1[[Blockhub.Ethereum.Ethereum, Blockhub.Ethereum]], Blockhub.Core","Wallet":{"$ref":"2"},"Address":"0x821aEa9a577a9b44299B9c15c88cf3087F3b5544","Id":"643f2adc-1a42-43a9-bf28-464289d921cd","Name":""},{"$id":"7","$type":"Blockhub.Wallet.Account`1[[Blockhub.Ethereum.Ethereum, Blockhub.Ethereum]], Blockhub.Core","Wallet":{"$ref":"2"},"Address":"0x0d1d4e623D10F9FBA5Db95830F7d3839406C6AF2","Id":"a29131b4-1f49-4ea1-a866-f13a2e29951a","Name":""},{"$id":"8","$type":"Blockhub.Wallet.Account`1[[Blockhub.Ethereum.Ethereum, Blockhub.Ethereum]], Blockhub.Core","Wallet":{"$ref":"2"},"Address":"0x2932b7A2355D6fecc4b5c0B6BD44cC31df247a2e","Id":"13440004-4495-4c3a-8981-84f5e6a244f9","Name":""},{"$id":"9","$type":"Blockhub.Wallet.Account`1[[Blockhub.Ethereum.Ethereum, Blockhub.Ethereum]], Blockhub.Core","Wallet":{"$ref":"2"},"Address":"0x2191eF87E392377ec08E7c08Eb105Ef5448eCED5","Id":"63390fbc-69d2-4660-a12b-7f973f61c506","Name":""},{"$id":"10","$type":"Blockhub.Wallet.Account`1[[Blockhub.Ethereum.Ethereum, Blockhub.Ethereum]], Blockhub.Core","Wallet":{"$ref":"2"},"Address":"0x0F4F2Ac550A1b4e2280d04c21cEa7EBD822934b5","Id":"b2c0ff78-0606-4598-935f-917ab36f3825","Name":""},{"$id":"11","$type":"Blockhub.Wallet.Account`1[[Blockhub.Ethereum.Ethereum, Blockhub.Ethereum]], Blockhub.Core","Wallet":{"$ref":"2"},"Address":"0x6330A553Fc93768F612722BB8c2eC78aC90B3bbc","Id":"06bf8073-a584-4203-b506-298e2d087b48","Name":""},{"$id":"12","$type":"Blockhub.Wallet.Account`1[[Blockhub.Ethereum.Ethereum, Blockhub.Ethereum]], Blockhub.Core","Wallet":{"$ref":"2"},"Address":"0x5AEDA56215b167893e80B4fE645BA6d5Bab767DE","Id":"40a31eda-78bb-4cb7-b600-335537e2b9e4","Name":""},{"$id":"13","$type":"Blockhub.Wallet.Account`1[[Blockhub.Ethereum.Ethereum, Blockhub.Ethereum]], Blockhub.Core","Wallet":{"$ref":"2"},"Address":"0xE44c4cf797505AF1527B11e4F4c6f95531b4Be24","Id":"abb2d5db-35de-48a4-91fd-2a07cb44f1ec","Name":""},{"$id":"14","$type":"Blockhub.Wallet.Account`1[[Blockhub.Ethereum.Ethereum, Blockhub.Ethereum]], Blockhub.Core","Wallet":{"$ref":"2"},"Address":"0x69e1CB5cFcA8A311586e3406ed0301C06fb839a2","Id":"3e6bb18c-e387-4b8e-b05f-81721081173a","Name":""},{"$id":"15","$type":"Blockhub.Wallet.Account`1[[Blockhub.Ethereum.Ethereum, Blockhub.Ethereum]], Blockhub.Core","Wallet":{"$ref":"2"},"Address":"0xF014343BDFFbED8660A9d8721deC985126f189F3","Id":"7c898412-0bf6-4604-b87f-0eedc987420f","Name":""},{"$id":"16","$type":"Blockhub.Wallet.Account`1[[Blockhub.Ethereum.Ethereum, Blockhub.Ethereum]], Blockhub.Core","Wallet":{"$ref":"2"},"Address":"0x0E79EDbD6A727CfeE09A2b1d0A59F7752d5bf7C9","Id":"665f2697-4927-422d-abc6-1e5004e8d138","Name":""},{"$id":"17","$type":"Blockhub.Wallet.Account`1[[Blockhub.Ethereum.Ethereum, Blockhub.Ethereum]], Blockhub.Core","Wallet":{"$ref":"2"},"Address":"0x9bC1169Ca09555bf2721A5C9eC6D69c8073bfeB4","Id":"b1d510c1-51a3-4122-ab15-fa99f18348df","Name":""},{"$id":"18","$type":"Blockhub.Wallet.Account`1[[Blockhub.Ethereum.Ethereum, Blockhub.Ethereum]], Blockhub.Core","Wallet":{"$ref":"2"},"Address":"0xa23eAEf02F9E0338EEcDa8Fdd0A73aDD781b2A86","Id":"7382a949-f050-431d-ac73-97243db78bc6","Name":""},{"$id":"19","$type":"Blockhub.Wallet.Account`1[[Blockhub.Ethereum.Ethereum, Blockhub.Ethereum]], Blockhub.Core","Wallet":{"$ref":"2"},"Address":"0xc449a27B106BE1120Bd1Fd62F8166A2F61588eb9","Id":"9ba7ebe1-ccf9-4eaf-a87a-48d5910fd5e9","Name":""},{"$id":"20","$type":"Blockhub.Wallet.Account`1[[Blockhub.Ethereum.Ethereum, Blockhub.Ethereum]], Blockhub.Core","Wallet":{"$ref":"2"},"Address":"0xF24AE9CE9B62d83059BD849b9F36d3f4792F5081","Id":"299aedc8-3f45-47d3-b8fd-80fc3d7e7ee9","Name":""},{"$id":"21","$type":"Blockhub.Wallet.Account`1[[Blockhub.Ethereum.Ethereum, Blockhub.Ethereum]], Blockhub.Core","Wallet":{"$ref":"2"},"Address":"0xc44B027a94913FB515B19F04CAf515e74AE24FD6","Id":"6662d47c-465c-4d7a-9260-697f2efdfb5d","Name":""},{"$id":"22","$type":"Blockhub.Wallet.Account`1[[Blockhub.Ethereum.Ethereum, Blockhub.Ethereum]], Blockhub.Core","Wallet":{"$ref":"2"},"Address":"0xcb0236B37Ff19001633E38808bd124b60B1fE1ba","Id":"256de5c0-4c74-4f0f-9fa2-474cbc637da1","Name":""},{"$id":"23","$type":"Blockhub.Wallet.Account`1[[Blockhub.Ethereum.Ethereum, Blockhub.Ethereum]], Blockhub.Core","Wallet":{"$ref":"2"},"Address":"0x715e632C0FE0d07D02fC3d2Cf630d11e1A45C522","Id":"ac312e1f-a9b2-409a-a605-e3da3426d04c","Name":""},{"$id":"24","$type":"Blockhub.Wallet.Account`1[[Blockhub.Ethereum.Ethereum, Blockhub.Ethereum]], Blockhub.Core","Wallet":{"$ref":"2"},"Address":"0x90FFD070a8333ACB4Ac1b8EBa59a77f9f1001819","Id":"8a71dbab-1ef6-4d59-8fc8-0972b370ae19","Name":""},{"$id":"25","$type":"Blockhub.Wallet.Account`1[[Blockhub.Ethereum.Ethereum, Blockhub.Ethereum]], Blockhub.Core","Wallet":{"$ref":"2"},"Address":"0x036945CD50df76077cb2D6CF5293B32252BCe247","Id":"06c98c2e-e3a7-40bd-9d06-02d23e500d44","Name":""},{"$id":"26","$type":"Blockhub.Wallet.Account`1[[Blockhub.Ethereum.Ethereum, Blockhub.Ethereum]], Blockhub.Core","Wallet":{"$ref":"2"},"Address":"0x23f0227FB09D50477331D2BB8519A38a52B9dFAF","Id":"842f765a-3ef7-43af-a4c4-638859a89ebf","Name":""},{"$id":"27","$type":"Blockhub.Wallet.Account`1[[Blockhub.Ethereum.Ethereum, Blockhub.Ethereum]], Blockhub.Core","Wallet":{"$ref":"2"},"Address":"0x799759c45265B96cac16b88A7084C068d38aFce9","Id":"d6ed6520-4a1a-4a03-a9db-7a02aa242ce0","Name":""},{"$id":"28","$type":"Blockhub.Wallet.Account`1[[Blockhub.Ethereum.Ethereum, Blockhub.Ethereum]], Blockhub.Core","Wallet":{"$ref":"2"},"Address":"0xA6BFE07B18Df9E42F0086D2FCe9334B701868314","Id":"63251e05-b061-4bcd-8278-d3ca5eb0f6fd","Name":""},{"$id":"29","$type":"Blockhub.Wallet.Account`1[[Blockhub.Ethereum.Ethereum, Blockhub.Ethereum]], Blockhub.Core","Wallet":{"$ref":"2"},"Address":"0x39Ae04B556bbdD73123Bab2d091DCD068144361F","Id":"3bbc0a92-50c9-4435-b7a7-e21e4b5e2005","Name":""},{"$id":"30","$type":"Blockhub.Wallet.Account`1[[Blockhub.Ethereum.Ethereum, Blockhub.Ethereum]], Blockhub.Core","Wallet":{"$ref":"2"},"Address":"0x068729ec4f46330d9Af83f2f5AF1B155d957BD42","Id":"72bd17b9-81ef-4a67-a155-c00a2373d60f","Name":""},{"$id":"31","$type":"Blockhub.Wallet.Account`1[[Blockhub.Ethereum.Ethereum, Blockhub.Ethereum]], Blockhub.Core","Wallet":{"$ref":"2"},"Address":"0x9EE19563Df46208d4C1a11c9171216012E9ba2D0","Id":"5c2fbb1c-64ce-492d-a609-9cd7ae6bff20","Name":""},{"$id":"32","$type":"Blockhub.Wallet.Account`1[[Blockhub.Ethereum.Ethereum, Blockhub.Ethereum]], Blockhub.Core","Wallet":{"$ref":"2"},"Address":"0x04ab41d3d5147c5d2BdC3BcFC5e62539fd7e428B","Id":"4eca22bc-c131-4ba3-84d4-850a9de1f5fa","Name":""},{"$id":"33","$type":"Blockhub.Wallet.Account`1[[Blockhub.Ethereum.Ethereum, Blockhub.Ethereum]], Blockhub.Core","Wallet":{"$ref":"2"},"Address":"0xeF264a86495fF640481D7AC16200A623c92D1E37","Id":"0194448a-3640-44e9-9dfe-9244524d5cdb","Name":""},{"$id":"34","$type":"Blockhub.Wallet.Account`1[[Blockhub.Ethereum.Ethereum, Blockhub.Ethereum]], Blockhub.Core","Wallet":{"$ref":"2"},"Address":"0x645FdC97c87c437da6b11b72471a703dF3702813","Id":"ac268f56-ddd8-45ea-93d1-a79d87cbbfdd","Name":""},{"$id":"35","$type":"Blockhub.Wallet.Account`1[[Blockhub.Ethereum.Ethereum, Blockhub.Ethereum]], Blockhub.Core","Wallet":{"$ref":"2"},"Address":"0xbE6f5bF50087332024634d028eCF896C7b482Ab1","Id":"f6a36979-9ce5-49ab-8645-2094faf06a81","Name":""},{"$id":"36","$type":"Blockhub.Wallet.Account`1[[Blockhub.Ethereum.Ethereum, Blockhub.Ethereum]], Blockhub.Core","Wallet":{"$ref":"2"},"Address":"0xcE527c7372B73C77F3A349bfBce74a6F5D800d8E","Id":"3fee6f9b-713f-4fd6-957f-881d641ace57","Name":""},{"$id":"37","$type":"Blockhub.Wallet.Account`1[[Blockhub.Ethereum.Ethereum, Blockhub.Ethereum]], Blockhub.Core","Wallet":{"$ref":"2"},"Address":"0x21ec0514bfFefF9E0EE317b8c87657E4a30F4Fb2","Id":"082c0574-2bcf-45c3-b035-2a561d4cebca","Name":""},{"$id":"38","$type":"Blockhub.Wallet.Account`1[[Blockhub.Ethereum.Ethereum, Blockhub.Ethereum]], Blockhub.Core","Wallet":{"$ref":"2"},"Address":"0xEAA2fc390D0eC1d047dCC1210a9Bf643d12de330","Id":"22b7cc5a-627b-47e1-9f2d-fad8986ff0c1","Name":""},{"$id":"39","$type":"Blockhub.Wallet.Account`1[[Blockhub.Ethereum.Ethereum, Blockhub.Ethereum]], Blockhub.Core","Wallet":{"$ref":"2"},"Address":"0xC5fa34ECBaF44181f1d144C13FBaEd69e76b80f1","Id":"3c5cfa96-7344-4e6a-b6e8-5ee9741d4246","Name":""},{"$id":"40","$type":"Blockhub.Wallet.Account`1[[Blockhub.Ethereum.Ethereum, Blockhub.Ethereum]], Blockhub.Core","Wallet":{"$ref":"2"},"Address":"0x4F388EE383f1634d952a5Ed8e032Dc27094f44FD","Id":"88d2d3dc-b4cf-49fb-90e5-a81b019d17c5","Name":""},{"$id":"41","$type":"Blockhub.Wallet.Account`1[[Blockhub.Ethereum.Ethereum, Blockhub.Ethereum]], Blockhub.Core","Wallet":{"$ref":"2"},"Address":"0xeEf5E3535aA39e0C2266BbA234E187adA9ed50A1","Id":"cb66aedf-7b03-4b00-b256-baa87c911e7f","Name":""},{"$id":"42","$type":"Blockhub.Wallet.Account`1[[Blockhub.Ethereum.Ethereum, Blockhub.Ethereum]], Blockhub.Core","Wallet":{"$ref":"2"},"Address":"0x6008E128477ceEE5561fE2dEAdD82564d29fD249","Id":"1054c0f1-8876-44e1-81b3-8e9a68e22be3","Name":""},{"$id":"43","$type":"Blockhub.Wallet.Account`1[[Blockhub.Ethereum.Ethereum, Blockhub.Ethereum]], Blockhub.Core","Wallet":{"$ref":"2"},"Address":"0xfEf504C230aA4c42707FcBFfa46aE640498BC2cb","Id":"7f779937-472f-424d-9032-608ae153a4d6","Name":""},{"$id":"44","$type":"Blockhub.Wallet.Account`1[[Blockhub.Ethereum.Ethereum, Blockhub.Ethereum]], Blockhub.Core","Wallet":{"$ref":"2"},"Address":"0x70C8F02D4e44d906e80a8d0b1591Ab569a20Ae9C","Id":"4370acce-1d43-4c60-a181-8a1aa9e9771f","Name":""},{"$id":"45","$type":"Blockhub.Wallet.Account`1[[Blockhub.Ethereum.Ethereum, Blockhub.Ethereum]], Blockhub.Core","Wallet":{"$ref":"2"},"Address":"0x53eF3e89950e97bAD7d027F41ab05debc7Bb5c74","Id":"1772b863-f1da-4dbb-9d53-ed76ab6cde79","Name":""},{"$id":"46","$type":"Blockhub.Wallet.Account`1[[Blockhub.Ethereum.Ethereum, Blockhub.Ethereum]], Blockhub.Core","Wallet":{"$ref":"2"},"Address":"0xE3c27A49b81a7D59DC516D58ab2E5ee6A545c008","Id":"d78f6784-c0da-43cd-9191-76829bd25241","Name":""},{"$id":"47","$type":"Blockhub.Wallet.Account`1[[Blockhub.Ethereum.Ethereum, Blockhub.Ethereum]], Blockhub.Core","Wallet":{"$ref":"2"},"Address":"0xc496E6FEACf5D7ee4E1609179fA4C1D1698116ec","Id":"a076942e-59aa-4acc-a61c-645713bde4eb","Name":""},{"$id":"48","$type":"Blockhub.Wallet.Account`1[[Blockhub.Ethereum.Ethereum, Blockhub.Ethereum]], Blockhub.Core","Wallet":{"$ref":"2"},"Address":"0x5598CA13044003326C25459B4E9B778922C8a00e","Id":"06abf625-5776-410d-8d34-624739f84b04","Name":""},{"$id":"49","$type":"Blockhub.Wallet.Account`1[[Blockhub.Ethereum.Ethereum, Blockhub.Ethereum]], Blockhub.Core","Wallet":{"$ref":"2"},"Address":"0x5Fb25C1c734D077fdFb603E9f586Bee11706a042","Id":"dcb5756d-38d6-4300-8d7a-bebe504ff99f","Name":""},{"$id":"50","$type":"Blockhub.Wallet.Account`1[[Blockhub.Ethereum.Ethereum, Blockhub.Ethereum]], Blockhub.Core","Wallet":{"$ref":"2"},"Address":"0x3E5a0f348C831b489deC1be087f8Ef182A4CfE54","Id":"fcb5b4b9-b014-401c-be44-59379d89aea4","Name":""},{"$id":"51","$type":"Blockhub.Wallet.Account`1[[Blockhub.Ethereum.Ethereum, Blockhub.Ethereum]], Blockhub.Core","Wallet":{"$ref":"2"},"Address":"0x6a90Ed741Fe4B87545a127879bA18F41FD17fdB5","Id":"995deb98-0cd2-4eb5-a89f-43ee9dbf2862","Name":""},{"$id":"52","$type":"Blockhub.Wallet.Account`1[[Blockhub.Ethereum.Ethereum, Blockhub.Ethereum]], Blockhub.Core","Wallet":{"$ref":"2"},"Address":"0xa1AD47355B994Cc18Bd709789055DeFD54e738E3","Id":"019f4acb-a7b2-45b3-951b-ca34cf879cd8","Name":""},{"$id":"53","$type":"Blockhub.Wallet.Account`1[[Blockhub.Ethereum.Ethereum, Blockhub.Ethereum]], Blockhub.Core","Wallet":{"$ref":"2"},"Address":"0x7c22D70Abcc54bB97b172f5FcF78D896B3406135","Id":"0d72ccc1-e98a-4d53-92e2-f06d16b13766","Name":""},{"$id":"54","$type":"Blockhub.Wallet.Account`1[[Blockhub.Ethereum.Ethereum, Blockhub.Ethereum]], Blockhub.Core","Wallet":{"$ref":"2"},"Address":"0x2c24BE8144ddF9f45c99288f6349b5c8500F628f","Id":"8eea0edb-d5d3-44f6-8930-90307c7871fd","Name":""},{"$id":"55","$type":"Blockhub.Wallet.Account`1[[Blockhub.Ethereum.Ethereum, Blockhub.Ethereum]], Blockhub.Core","Wallet":{"$ref":"2"},"Address":"0xa3f946F2e9e30f00b45FE0791C31F7B64A571b2f","Id":"0a0a9859-7fed-41af-8aca-30af04fd650b","Name":""},{"$id":"56","$type":"Blockhub.Wallet.Account`1[[Blockhub.Ethereum.Ethereum, Blockhub.Ethereum]], Blockhub.Core","Wallet":{"$ref":"2"},"Address":"0x6FEba51DCD19CA406F1265bD7eC5178103aF55C2","Id":"ff4234ea-24f1-4525-96c7-b114cfb8f1bb","Name":""},{"$id":"57","$type":"Blockhub.Wallet.Account`1[[Blockhub.Ethereum.Ethereum, Blockhub.Ethereum]], Blockhub.Core","Wallet":{"$ref":"2"},"Address":"0xAafCa8e6b0e49e2a22AC3B6565041d5cb59dF242","Id":"617c62ba-2add-429d-9060-f3e67ce3be38","Name":""},{"$id":"58","$type":"Blockhub.Wallet.Account`1[[Blockhub.Ethereum.Ethereum, Blockhub.Ethereum]], Blockhub.Core","Wallet":{"$ref":"2"},"Address":"0xDb6388B2F66e6816386959e60e2D34A8a3909578","Id":"d5ce9194-b751-40ea-938d-c00b5d2bebdd","Name":""},{"$id":"59","$type":"Blockhub.Wallet.Account`1[[Blockhub.Ethereum.Ethereum, Blockhub.Ethereum]], Blockhub.Core","Wallet":{"$ref":"2"},"Address":"0x27E53C8f3863e9a2C070b7fE842aD926cD49Db2F","Id":"4164dd63-1270-46be-9def-a3644846dfe3","Name":""},{"$id":"60","$type":"Blockhub.Wallet.Account`1[[Blockhub.Ethereum.Ethereum, Blockhub.Ethereum]], Blockhub.Core","Wallet":{"$ref":"2"},"Address":"0xE8182F4e9378349D8148bA8C82A51f61392D753e","Id":"2e3f320d-5db8-4aa3-a639-6e4b2302e4df","Name":""},{"$id":"61","$type":"Blockhub.Wallet.Account`1[[Blockhub.Ethereum.Ethereum, Blockhub.Ethereum]], Blockhub.Core","Wallet":{"$ref":"2"},"Address":"0xFEd6014661477bA594Ff0A2dBa1EC970ef8c3bC9","Id":"d2cc2eb6-abbb-4434-afca-7044cd19a986","Name":""},{"$id":"62","$type":"Blockhub.Wallet.Account`1[[Blockhub.Ethereum.Ethereum, Blockhub.Ethereum]], Blockhub.Core","Wallet":{"$ref":"2"},"Address":"0x3f7632EF242f7492C2860296960b7c31A9474Fd5","Id":"37bfe312-74d8-4415-acd3-94ac7c6b6c4f","Name":""},{"$id":"63","$type":"Blockhub.Wallet.Account`1[[Blockhub.Ethereum.Ethereum, Blockhub.Ethereum]], Blockhub.Core","Wallet":{"$ref":"2"},"Address":"0xBE0138d90839f3e78cA6df97a83f71d0c2725De4","Id":"4ff19a46-a80c-4495-a260-b4892dd13cff","Name":""},{"$id":"64","$type":"Blockhub.Wallet.Account`1[[Blockhub.Ethereum.Ethereum, Blockhub.Ethereum]], Blockhub.Core","Wallet":{"$ref":"2"},"Address":"0xEB48C891256E49662f60f8d0367aF51803A99f98","Id":"d7cf528b-2b80-4992-9e67-25ae468741f7","Name":""},{"$id":"65","$type":"Blockhub.Wallet.Account`1[[Blockhub.Ethereum.Ethereum, Blockhub.Ethereum]], Blockhub.Core","Wallet":{"$ref":"2"},"Address":"0x2924176c979b7491FE6eA6a5d100A9291E12e33c","Id":"83f5c20e-566e-4c29-ba9f-926b23749dc4","Name":""},{"$id":"66","$type":"Blockhub.Wallet.Account`1[[Blockhub.Ethereum.Ethereum, Blockhub.Ethereum]], Blockhub.Core","Wallet":{"$ref":"2"},"Address":"0xD7f1E3aCdc33566363316B7553Aa558CbCaE260e","Id":"cd573f5a-811e-40bd-ad2c-3aefa22cd2f7","Name":""},{"$id":"67","$type":"Blockhub.Wallet.Account`1[[Blockhub.Ethereum.Ethereum, Blockhub.Ethereum]], Blockhub.Core","Wallet":{"$ref":"2"},"Address":"0x1b8FA770f013173Ee66dA32E3836918aa39efB77","Id":"95cb5cf4-598a-4299-8163-2544685a85ee","Name":""},{"$id":"68","$type":"Blockhub.Wallet.Account`1[[Blockhub.Ethereum.Ethereum, Blockhub.Ethereum]], Blockhub.Core","Wallet":{"$ref":"2"},"Address":"0x4f6a07Ab35b1b9c8c0613185002F98B8D8990c3F","Id":"5b80012e-f4eb-4856-9eee-bbd5fcd2b83f","Name":""},{"$id":"69","$type":"Blockhub.Wallet.Account`1[[Blockhub.Ethereum.Ethereum, Blockhub.Ethereum]], Blockhub.Core","Wallet":{"$ref":"2"},"Address":"0xdf230F62739beDcB1BED428906232a44Bc37De3a","Id":"5c30c7d9-a4b5-47a0-9c95-8acf9d132f1b","Name":""},{"$id":"70","$type":"Blockhub.Wallet.Account`1[[Blockhub.Ethereum.Ethereum, Blockhub.Ethereum]], Blockhub.Core","Wallet":{"$ref":"2"},"Address":"0xd9fFF40762dD21703D33E9E3e16553dCF452Ad41","Id":"f94557df-cb58-4442-ba8e-811c23cac28e","Name":""},{"$id":"71","$type":"Blockhub.Wallet.Account`1[[Blockhub.Ethereum.Ethereum, Blockhub.Ethereum]], Blockhub.Core","Wallet":{"$ref":"2"},"Address":"0x4A5446ACE419aF2261D1C0B599E59a09e67b1C41","Id":"96288288-56d3-4652-93ee-cf497c265096","Name":""},{"$id":"72","$type":"Blockhub.Wallet.Account`1[[Blockhub.Ethereum.Ethereum, Blockhub.Ethereum]], Blockhub.Core","Wallet":{"$ref":"2"},"Address":"0xeE9eDbbFD46D4F330857295ad59632649F45Cf6C","Id":"af61b3b7-17e8-4dd8-be93-5bf6179ea3c1","Name":""},{"$id":"73","$type":"Blockhub.Wallet.Account`1[[Blockhub.Ethereum.Ethereum, Blockhub.Ethereum]], Blockhub.Core","Wallet":{"$ref":"2"},"Address":"0x4016e2585E3DB4a0d9d5B7F0266A95Cfa9b8BfaE","Id":"f2da57b0-1a12-4557-bc9e-ff5e42b8920c","Name":""},{"$id":"74","$type":"Blockhub.Wallet.Account`1[[Blockhub.Ethereum.Ethereum, Blockhub.Ethereum]], Blockhub.Core","Wallet":{"$ref":"2"},"Address":"0x1005a8fb0c2501180486E0544D199725cFD218F4","Id":"c498db86-511b-4b9c-8a44-754e9c16a7fd","Name":""},{"$id":"75","$type":"Blockhub.Wallet.Account`1[[Blockhub.Ethereum.Ethereum, Blockhub.Ethereum]], Blockhub.Core","Wallet":{"$ref":"2"},"Address":"0x27b439aB6e029BE399059466989601206919a3e4","Id":"2b543f93-653e-4efb-807d-74f61fb205e9","Name":""},{"$id":"76","$type":"Blockhub.Wallet.Account`1[[Blockhub.Ethereum.Ethereum, Blockhub.Ethereum]], Blockhub.Core","Wallet":{"$ref":"2"},"Address":"0x99F96044b954Af5C4969cB0c129Fcf407f90A632","Id":"6c72bdb8-24e5-45cf-8b96-8a2e81e3a21a","Name":""},{"$id":"77","$type":"Blockhub.Wallet.Account`1[[Blockhub.Ethereum.Ethereum, Blockhub.Ethereum]], Blockhub.Core","Wallet":{"$ref":"2"},"Address":"0x38B7584dbFf65a8599fb6b1ebD08B3d8cc16F797","Id":"842b39d8-be53-4191-a394-f1a438e5c5e8","Name":""},{"$id":"78","$type":"Blockhub.Wallet.Account`1[[Blockhub.Ethereum.Ethereum, Blockhub.Ethereum]], Blockhub.Core","Wallet":{"$ref":"2"},"Address":"0x5Cec2a9F56952405Fe7F845Fe2E731ef9D460a9c","Id":"a92b371e-37e3-4185-bdcf-c6a5a0ae8838","Name":""},{"$id":"79","$type":"Blockhub.Wallet.Account`1[[Blockhub.Ethereum.Ethereum, Blockhub.Ethereum]], Blockhub.Core","Wallet":{"$ref":"2"},"Address":"0xA43029cBb00427186357BE8aF43335A29a34BC0b","Id":"c349ec26-c28a-45ed-a1a9-85d9a218e0f6","Name":""},{"$id":"80","$type":"Blockhub.Wallet.Account`1[[Blockhub.Ethereum.Ethereum, Blockhub.Ethereum]], Blockhub.Core","Wallet":{"$ref":"2"},"Address":"0x7b2681B998A86eBF8150229B9651fa0233D8814d","Id":"31ac7306-a0ac-476b-8c2c-615a37003d97","Name":""},{"$id":"81","$type":"Blockhub.Wallet.Account`1[[Blockhub.Ethereum.Ethereum, Blockhub.Ethereum]], Blockhub.Core","Wallet":{"$ref":"2"},"Address":"0x2c8D36FE19a6Ca7440e84BfecD905F9f9A6a7df9","Id":"5eaa1496-9aa8-4da1-a7f1-bc79e559f5b9","Name":""},{"$id":"82","$type":"Blockhub.Wallet.Account`1[[Blockhub.Ethereum.Ethereum, Blockhub.Ethereum]], Blockhub.Core","Wallet":{"$ref":"2"},"Address":"0x0cD9D0cB4BD933c1D64aEF87B1e84F163a2C0553","Id":"0dd3d91b-4963-441a-a740-ed6809292348","Name":""},{"$id":"83","$type":"Blockhub.Wallet.Account`1[[Blockhub.Ethereum.Ethereum, Blockhub.Ethereum]], Blockhub.Core","Wallet":{"$ref":"2"},"Address":"0x99180d6AedDfd94fc796a227EE34DFE22078aE5e","Id":"c83ac05b-3670-410c-b6e8-2ac33814e220","Name":""},{"$id":"84","$type":"Blockhub.Wallet.Account`1[[Blockhub.Ethereum.Ethereum, Blockhub.Ethereum]], Blockhub.Core","Wallet":{"$ref":"2"},"Address":"0xcaB1c7A9eE99A655BDa5D1b625763C3c807BFEDe","Id":"9cd10464-f2d0-4432-9e3b-580d3f4accca","Name":""},{"$id":"85","$type":"Blockhub.Wallet.Account`1[[Blockhub.Ethereum.Ethereum, Blockhub.Ethereum]], Blockhub.Core","Wallet":{"$ref":"2"},"Address":"0x9CBB0B5ffd362c353B6f2D81bd38079396b97CDC","Id":"7db22d77-6de3-4ff3-adb6-23189af50b13","Name":""},{"$id":"86","$type":"Blockhub.Wallet.Account`1[[Blockhub.Ethereum.Ethereum, Blockhub.Ethereum]], Blockhub.Core","Wallet":{"$ref":"2"},"Address":"0x3954f1d3F4355E0dc3fb68d89827B5831D3A2322","Id":"ee1f6100-b601-4331-aaee-000868ab34b2","Name":""},{"$id":"87","$type":"Blockhub.Wallet.Account`1[[Blockhub.Ethereum.Ethereum, Blockhub.Ethereum]], Blockhub.Core","Wallet":{"$ref":"2"},"Address":"0x38A17A4206d500877d478BF22e3bc7b378aB6C44","Id":"4a7a75a3-e003-4de6-b916-c24eaae847a6","Name":""},{"$id":"88","$type":"Blockhub.Wallet.Account`1[[Blockhub.Ethereum.Ethereum, Blockhub.Ethereum]], Blockhub.Core","Wallet":{"$ref":"2"},"Address":"0x243903f923397f46B4bdEa61A4C324E6C328A217","Id":"032095f8-d93e-4c2c-a094-a9a1457c10d2","Name":""},{"$id":"89","$type":"Blockhub.Wallet.Account`1[[Blockhub.Ethereum.Ethereum, Blockhub.Ethereum]], Blockhub.Core","Wallet":{"$ref":"2"},"Address":"0x9Ad91b22A214d52Ea0aB068E9B1B3c3F41479385","Id":"d3402d48-8c0b-4504-bf6c-3a03e1388acc","Name":""},{"$id":"90","$type":"Blockhub.Wallet.Account`1[[Blockhub.Ethereum.Ethereum, Blockhub.Ethereum]], Blockhub.Core","Wallet":{"$ref":"2"},"Address":"0x973A8c93872794B69b7dE8aAC48273278C5b7BBB","Id":"6bd92570-7e56-449a-82d8-f3896b14b19f","Name":""},{"$id":"91","$type":"Blockhub.Wallet.Account`1[[Blockhub.Ethereum.Ethereum, Blockhub.Ethereum]], Blockhub.Core","Wallet":{"$ref":"2"},"Address":"0x767FB55673CF802ad4Ed3D331180371E17B66DAD","Id":"7165e4f5-bbf1-49b1-baaa-c243c0b670db","Name":""},{"$id":"92","$type":"Blockhub.Wallet.Account`1[[Blockhub.Ethereum.Ethereum, Blockhub.Ethereum]], Blockhub.Core","Wallet":{"$ref":"2"},"Address":"0x2F9DF293d1bf13FaD9eb390BB842299e41Bed561","Id":"6c041549-4dfa-4c8f-b9e8-b878b753e238","Name":""},{"$id":"93","$type":"Blockhub.Wallet.Account`1[[Blockhub.Ethereum.Ethereum, Blockhub.Ethereum]], Blockhub.Core","Wallet":{"$ref":"2"},"Address":"0xb2ddED06c43dcA21C57244617c7f7a9d84579FDE","Id":"1602bc4d-4a23-460b-9dc3-282b30643ffe","Name":""},{"$id":"94","$type":"Blockhub.Wallet.Account`1[[Blockhub.Ethereum.Ethereum, Blockhub.Ethereum]], Blockhub.Core","Wallet":{"$ref":"2"},"Address":"0x1B0B69172bAd8ce9277120E3DE285e35278202e8","Id":"941876d2-4103-485a-97d2-9ea6c798d21d","Name":""},{"$id":"95","$type":"Blockhub.Wallet.Account`1[[Blockhub.Ethereum.Ethereum, Blockhub.Ethereum]], Blockhub.Core","Wallet":{"$ref":"2"},"Address":"0x7d902745B78Ac21DbE042Aa35939af4132778A6C","Id":"2a846d28-460a-4618-bf13-a72bfc036817","Name":""},{"$id":"96","$type":"Blockhub.Wallet.Account`1[[Blockhub.Ethereum.Ethereum, Blockhub.Ethereum]], Blockhub.Core","Wallet":{"$ref":"2"},"Address":"0xB6E565b4ad4e11a6B129d58326Ec4c7d22e4Ea98","Id":"a4a9c3ae-abb6-45b0-b9da-207055110e10","Name":""},{"$id":"97","$type":"Blockhub.Wallet.Account`1[[Blockhub.Ethereum.Ethereum, Blockhub.Ethereum]], Blockhub.Core","Wallet":{"$ref":"2"},"Address":"0x0bAE34BC2D2dED3A3C4F7a9C35F3197C8e2C1986","Id":"062308e3-2d41-47c7-baf0-62cf9799c941","Name":""},{"$id":"98","$type":"Blockhub.Wallet.Account`1[[Blockhub.Ethereum.Ethereum, Blockhub.Ethereum]], Blockhub.Core","Wallet":{"$ref":"2"},"Address":"0xC2fA1bACE4DDA22d84a466884493Fad6f71E0275","Id":"0a8130fe-c624-4153-9c45-099770b9c995","Name":""},{"$id":"99","$type":"Blockhub.Wallet.Account`1[[Blockhub.Ethereum.Ethereum, Blockhub.Ethereum]], Blockhub.Core","Wallet":{"$ref":"2"},"Address":"0xcBFfa1EE1E37EE59923C444C727c54720c774C62","Id":"1a1c4070-28ae-40ce-b4d1-332284d98590","Name":""},{"$id":"100","$type":"Blockhub.Wallet.Account`1[[Blockhub.Ethereum.Ethereum, Blockhub.Ethereum]], Blockhub.Core","Wallet":{"$ref":"2"},"Address":"0xCfa760C770686a06669c01EbAED9b92D37794d4C","Id":"7faf3cb7-0e9a-427f-87ec-2531dde6efb3","Name":""},{"$id":"101","$type":"Blockhub.Wallet.Account`1[[Blockhub.Ethereum.Ethereum, Blockhub.Ethereum]], Blockhub.Core","Wallet":{"$ref":"2"},"Address":"0x6557f2bedDCE2a2A54610Ded9959c2AEbA112904","Id":"3fb285e1-6e51-469e-bc95-8404c9258917","Name":""},{"$id":"102","$type":"Blockhub.Wallet.Account`1[[Blockhub.Ethereum.Ethereum, Blockhub.Ethereum]], Blockhub.Core","Wallet":{"$ref":"2"},"Address":"0x1B0A272Dc71CcD96685ae33266EA0c1264d3B670","Id":"6fd6c001-9d57-41de-8a7f-3e06e66120f5","Name":""}]},"Secret":"candy maple cake sugar pudding cream honey rich smooth crumble sweet treat","Id":"5fbd2e63-134c-4bb6-acee-eda70f7fdaa7","Name":"Test Wallet"}]},"Id":"df0c3364-4db3-4fca-9a47-8d7ecd6840d4","Name":"General Profile"}